heirarchical_leiden/__init__.py
heirarchical_leiden/hierarchical_leiden.py
heirarchical_leiden/leiden.py
heirarchical_leiden/quality_functions.py
heirarchical_leiden/utils.py
hierarchical_leiden-0.2.0.dist-info/METADATA
hierarchical_leiden-0.2.0.dist-info/WHEEL
hierarchical_leiden-0.2.0.dist-info/entry_points.txt
hierarchical_leiden-0.2.0.dist-info/RECORD
