Metadata-Version: 2.1
Name: hierarchical-leiden
Version: 0.2.0
Summary: Implementation of the hierarchical Leiden community detection algorithms.
Author-Email: Daniel Albert <git+community-detection+252b9@esclear.de>, Yanli <mail@yanli.one>
License: EUPL-1.2
Requires-Python: >=3.10
Requires-Dist: networkx>=3.0
Provides-Extra: demo
Requires-Dist: ipynb>=0.5.1; extra == "demo"
Requires-Dist: jupyter>=1.1.1; extra == "demo"
Requires-Dist: matplotlib>=3.10.3; extra == "demo"
